[{"imdb_id": "nm0154164", "actor": "Soumitra Chatterjee"}, {"imdb_id": "nm0846616", "actor": "Sharmila Tagore"}, {"imdb_id": "nm0149845", "actor": "Alok Chakravarty"}, {"imdb_id": "nm0611575", "actor": "Swapan Mukherjee"}, {"imdb_id": "nm5576481", "actor": "Tushar Bandyopadhyay"}, {"imdb_id": "nm4897797", "actor": "Gupi Banerjee"}, {"imdb_id": "nm1434574", "actor": "Panchanan Bhattacharya"}, {"imdb_id": "nm0080370", "actor": "Shanti Bhattacherjee"}, {"imdb_id": "nm5576471", "actor": "Jiten Bhons"}, {"imdb_id": "nm0154107", "actor": "Abhijit Chatterjee"}, {"imdb_id": "nm0154132", "actor": "Jogesh Chatterjee"}, {"imdb_id": "nm0222439", "actor": "Asha Devi"}, {"imdb_id": "nm0067570", "actor": "Belarani Devi"}, {"imdb_id": "nm0222490", "actor": "Sefalika Devi"}, {"imdb_id": "nm5576537", "actor": "Biren Ghosh"}]