[{"imdb_id": "nm0712546", "actor": "Paresh Rawal"}, {"imdb_id": "nm1946407", "actor": "Kay Kay Menon"}, {"imdb_id": "nm0451234", "actor": "Irrfan Khan"}, {"imdb_id": "nm0534856", "actor": "Madhavan"}, {"imdb_id": "nm1675786", "actor": "Soha Ali Khan"}, {"imdb_id": "nm3237860", "actor": "Sachin Pathak"}, {"imdb_id": "nm3001807", "actor": "Santosh Juvekar"}, {"imdb_id": "nm3253318", "actor": "Kavin Dave"}, {"imdb_id": "nm3253131", "actor": "Syed Rizwan Ahmed"}, {"imdb_id": "nm1274869", "actor": "Rajesh Bhosle"}, {"imdb_id": "nm3252731", "actor": "Saksham Dayma"}, {"imdb_id": "nm3253964", "actor": "Aakash"}, {"imdb_id": "nm3252857", "actor": "Jeetendra Rai"}, {"imdb_id": "nm1282863", "actor": "Sameer Dharmadhikari"}, {"imdb_id": "nm3250873", "actor": "Gaurav Dhir"}]