[{"imdb_id": "nm1333687", "actor": "Dhanush"}, {"imdb_id": "nm0764853", "actor": "Saranya Ponvannan"}, {"imdb_id": "nm3898762", "actor": "Amala Paul"}, {"imdb_id": "nm2284321", "actor": "Samuthirakani"}, {"imdb_id": "nm0900266", "actor": "Vivek"}, {"imdb_id": "nm6120872", "actor": "Surabhi"}, {"imdb_id": "nm6632190", "actor": "Amitash"}, {"imdb_id": "nm4819263", "actor": "Cell Murugan"}, {"imdb_id": "nm6632191", "actor": "Hrishikesh"}, {"imdb_id": "nm6046821", "actor": "Sriram"}, {"imdb_id": "nm1572739", "actor": "Meera Krishna"}, {"imdb_id": "nm4174626", "actor": "Vignesh Shivan"}, {"imdb_id": "nm7824428", "actor": "Amitash Pradhan"}]